distkv/__init__.py
distkv/client.py
distkv/code.py
distkv/codec.py
distkv/config.py
distkv/data.py
distkv/default.py
distkv/errors.py
distkv/exceptions.py
distkv/model.py
distkv/runner.py
distkv/server.py
distkv/types.py
distkv/actor/__init__.py
distkv/actor/deletor.py
distkv/auth/__init__.py
distkv/auth/_test.py
distkv/auth/password.py
distkv/auth/root.py
distkv/backend/__init__.py
distkv/backend/mqtt.py
distkv/backend/serf.py
distkv/command/__init__.py
distkv/command/server.py
distkv/command/client/__init__.py
distkv/command/client/acl.py
distkv/command/client/auth.py
distkv/command/client/code.py
distkv/command/client/codec.py
distkv/command/client/data.py
distkv/command/client/error.py
distkv/command/client/internal.py
distkv/command/client/job.py
distkv/command/client/log.py
distkv/command/client/type.py
distkv/command/dump/__init__.py
distkv/mock/__init__.py
distkv/mock/mqtt.py
distkv/mock/serf.py
distkv/mock/tracer.py
distkv/obj/__init__.py
distkv/obj/command.py
distkv_ext/dummy/__init__.py
tests/__init__.py
tests/conftest.py
tests/test_basic.py
tests/test_basic_serf.py
tests/test_feature_acl.py
tests/test_feature_allrunner.py
tests/test_feature_auth.py
tests/test_feature_code.py
tests/test_feature_config.py
tests/test_feature_convert.py
tests/test_feature_dh.py
tests/test_feature_error.py
tests/test_feature_mirror.py
tests/test_feature_runner.py
tests/test_feature_singlerunner.py
tests/test_feature_ssl.py
tests/test_feature_typecheck.py
tests/test_kill.py
tests/test_load_save.py
tests/test_multi.py
tests/test_passthru.py
tests/test_recover.py
distkv-0.65.0.dist-info/LICENSE
distkv-0.65.0.dist-info/LICENSE.APACHE2
distkv-0.65.0.dist-info/LICENSE.MIT
distkv-0.65.0.dist-info/METADATA
distkv-0.65.0.dist-info/WHEEL
distkv-0.65.0.dist-info/entry_points.txt
distkv-0.65.0.dist-info/top_level.txt
distkv-0.65.0.dist-info/zip-safe
distkv-0.65.0.dist-info/RECORD
