Metadata-Version: 2.1
Name: distkv
Version: 0.65.0
Summary: A distributed no-master key-value store
Home-page: https://github.com/smurfix/distkv
Author: Matthias Urlichs
Author-email: matthias@urlichs.de
License: MIT -or- Apache License 2.0
Keywords: async,key-values,distributed
Classifier: Development Status :: 4 - Beta
Classifier: Intended Audience :: Information Technology
Classifier: License :: OSI Approved :: MIT License
Classifier: License :: OSI Approved :: Apache Software License
Classifier: Framework :: AsyncIO
Classifier: Framework :: Trio
Classifier: Operating System :: POSIX :: Linux
Classifier: Operating System :: MacOS :: MacOS X
Classifier: Operating System :: Microsoft :: Windows
Classifier: Programming Language :: Python :: 3.7
Classifier: Programming Language :: Python :: 3.8
Classifier: Programming Language :: Python :: Implementation :: CPython
Classifier: Topic :: Database
Classifier: Topic :: Home Automation
Classifier: Topic :: System :: Distributed Computing
Requires-Python: >=3.8
License-File: LICENSE
License-File: LICENSE.APACHE2
License-File: LICENSE.MIT
Requires-Dist: PyNaCl (>=1.3)
Requires-Dist: anyio (>=3)
Requires-Dist: asyncactor (>=0.21)
Requires-Dist: asyncclick (>7.99)
Requires-Dist: asyncscope (>=0.10.4)
Requires-Dist: asyncserf (>=0.16)
Requires-Dist: attrs (>=20)
Requires-Dist: jsonschema (>=2.5)
Requires-Dist: moat-lib-diffiehellman
Requires-Dist: moat-mqtt (>=0.32.1)
Requires-Dist: moat-util (>=0.34.0)
Requires-Dist: psutil
Requires-Dist: range-set (>=0.2)
Requires-Dist: ruyaml (>=0.89)
Requires-Dist: simpleeval (>=0.9.10)
Requires-Dist: trio (>=0.18)
Requires-Dist: exceptiongroup ; python_version < "3.11"
